LICENSE
MANIFEST.in
README.rst
setup.py
django_dev_protector/__init__.py
django_dev_protector/apps.py
django_dev_protector/middleware.py
django_dev_protector/settings.py
django_dev_protector/setup.py
django_dev_protector/tests.py
django_dev_protector.egg-info/PKG-INFO
django_dev_protector.egg-info/SOURCES.txt
django_dev_protector.egg-info/dependency_links.txt
django_dev_protector.egg-info/top_level.txt
django_dev_protector/templates/django_dev_protector/index.html